{"v":"5.6.10","fr":60,"ip":0,"op":451,"w":120,"h":120,"nm":"progressindicator_count","ddd":0,"assets":[{"id":"comp_0","layers":[{"ddd":0,"ind":2,"ty":0,"nm":"Count_unit2","refId":"comp_1","sr":1,"ks":{"o":{"a":0,"k":100,"ix":11},"r":{"a":0,"k":0,"ix":10},"p":{"a":0,"k":[12.5,18,0],"ix":2},"a":{"a":0,"k":[12.5,18,0],"ix":1},"s":{"a":0,"k":[100,100,100],"ix":6}},"ao":0,"w":25,"h":36,"ip":0,"op":600,"st":0,"bm":0},{"ddd":0,"ind":3,"ty":0,"nm":"Count_unit1","refId":"comp_3","sr":1,"ks":{"o":{"a":0,"k":100,"ix":11},"r":{"a":0,"k":0,"ix":10},"p":{"a":0,"k":[37.5,18,0],"ix":2},"a":{"a":0,"k":[12.5,18,0],"ix":1},"s":{"a":0,"k":[100,100,100],"ix":6}},"ao":0,"w":25,"h":36,"ip":360,"op":449,"st":360,"bm":0},{"ddd":0,"ind":4,"ty":0,"nm":"Count_unit1","refId":"comp_3","sr":1,"ks":{"o":{"a":0,"k":100,"ix":11},"r":{"a":0,"k":0,"ix":10},"p":{"a":0,"k":[37.5,18,0],"ix":2},"a":{"a":0,"k":[12.5,18,0],"ix":1},"s":{"a":0,"k":[100,100,100],"ix":6}},"ao":0,"w":25,"h":36,"ip":320,"op":360,"st":320,"bm":0},{"ddd":0,"ind":5,"ty":0,"nm":"Count_unit1","refId":"comp_3","sr":1,"ks":{"o":{"a":0,"k":100,"ix":11},"r":{"a":0,"k":0,"ix":10},"p":{"a":0,"k":[37.5,18,0],"ix":2},"a":{"a":0,"k":[12.5,18,0],"ix":1},"s":{"a":0,"k":[100,100,100],"ix":6}},"ao":0,"w":25,"h":36,"ip":280,"op":320,"st":280,"bm":0},{"ddd":0,"ind":6,"ty":0,"nm":"Count_unit1","refId":"comp_3","sr":1,"ks":{"o":{"a":0,"k":100,"ix":11},"r":{"a":0,"k":0,"ix":10},"p":{"a":0,"k":[37.5,18,0],"ix":2},"a":{"a":0,"k":[12.5,18,0],"ix":1},"s":{"a":0,"k":[100,100,100],"ix":6}},"ao":0,"w":25,"h":36,"ip":240,"op":280,"st":240,"bm":0},{"ddd":0,"ind":7,"ty":0,"nm":"Count_unit1","refId":"comp_3","sr":1,"ks":{"o":{"a":0,"k":100,"ix":11},"r":{"a":0,"k":0,"ix":10},"p":{"a":0,"k":[37.5,18,0],"ix":2},"a":{"a":0,"k":[12.5,18,0],"ix":1},"s":{"a":0,"k":[100,100,100],"ix":6}},"ao":0,"w":25,"h":36,"ip":200,"op":240,"st":200,"bm":0},{"ddd":0,"ind":8,"ty":0,"nm":"Count_unit1","refId":"comp_3","sr":1,"ks":{"o":{"a":0,"k":100,"ix":11},"r":{"a":0,"k":0,"ix":10},"p":{"a":0,"k":[37.5,18,0],"ix":2},"a":{"a":0,"k":[12.5,18,0],"ix":1},"s":{"a":0,"k":[100,100,100],"ix":6}},"ao":0,"w":25,"h":36,"ip":160,"op":200,"st":160,"bm":0},{"ddd":0,"ind":9,"ty":0,"nm":"Count_unit1","refId":"comp_3","sr":1,"ks":{"o":{"a":0,"k":100,"ix":11},"r":{"a":0,"k":0,"ix":10},"p":{"a":0,"k":[37.5,18,0],"ix":2},"a":{"a":0,"k":[12.5,18,0],"ix":1},"s":{"a":0,"k":[100,100,100],"ix":6}},"ao":0,"w":25,"h":36,"ip":120,"op":160,"st":120,"bm":0},{"ddd":0,"ind":10,"ty":0,"nm":"Count_unit1","refId":"comp_3","sr":1,"ks":{"o":{"a":0,"k":100,"ix":11},"r":{"a":0,"k":0,"ix":10},"p":{"a":0,"k":[37.5,18,0],"ix":2},"a":{"a":0,"k":[12.5,18,0],"ix":1},"s":{"a":0,"k":[100,100,100],"ix":6}},"ao":0,"w":25,"h":36,"ip":80,"op":120,"st":80,"bm":0},{"ddd":0,"ind":11,"ty":0,"nm":"Count_unit1","refId":"comp_3","sr":1,"ks":{"o":{"a":0,"k":100,"ix":11},"r":{"a":0,"k":0,"ix":10},"p":{"a":0,"k":[37.5,18,0],"ix":2},"a":{"a":0,"k":[12.5,18,0],"ix":1},"s":{"a":0,"k":[100,100,100],"ix":6}},"ao":0,"w":25,"h":36,"ip":40,"op":80,"st":40,"bm":0},{"ddd":0,"ind":12,"ty":0,"nm":"Count_unit1","refId":"comp_3","sr":1,"ks":{"o":{"a":0,"k":100,"ix":11},"r":{"a":0,"k":0,"ix":10},"p":{"a":0,"k":[37.5,18,0],"ix":2},"a":{"a":0,"k":[12.5,18,0],"ix":1},"s":{"a":0,"k":[100,100,100],"ix":6}},"ao":0,"w":25,"h":36,"ip":0,"op":40,"st":0,"bm":0}]},{"id":"comp_1","layers":[{"ddd":0,"ind":1,"ty":0,"nm":"Num03","refId":"comp_2","sr":1,"ks":{"o":{"a":0,"k":100,"ix":11},"r":{"a":0,"k":0,"ix":10},"p":{"a":1,"k":[{"i":{"x":0.833,"y":0.833},"o":{"x":0.167,"y":0.167},"t":30,"s":[12.5,180.5,0],"to":[0,-5.5,0],"ti":[0,5.5,0]},{"t":40,"s":[12.5,147.5,0],"h":1},{"i":{"x":0.833,"y":0.833},"o":{"x":0.167,"y":0.167},"t":70,"s":[12.5,147.5,0],"to":[0,-5.167,0],"ti":[0,5.167,0]},{"t":80,"s":[12.5,116.5,0],"h":1},{"i":{"x":0.833,"y":0.833},"o":{"x":0.167,"y":0.167},"t":110,"s":[12.5,116.5,0],"to":[0,-5.333,0],"ti":[0,5.333,0]},{"t":120,"s":[12.5,84.5,0],"h":1},{"i":{"x":0.833,"y":0.833},"o":{"x":0.167,"y":0.167},"t":150,"s":[12.5,84.5,0],"to":[0,-5.333,0],"ti":[0,5.333,0]},{"t":160,"s":[12.5,52.5,0],"h":1},{"i":{"x":0.833,"y":0.833},"o":{"x":0.167,"y":0.167},"t":190,"s":[12.5,52.5,0],"to":[0,-5.333,0],"ti":[0,5.333,0]},{"t":200,"s":[12.5,20.5,0],"h":1},{"i":{"x":0.833,"y":0.833},"o":{"x":0.167,"y":0.167},"t":230,"s":[12.5,20.5,0],"to":[0,-5.333,0],"ti":[0,5.333,0]},{"t":240,"s":[12.5,-11.5,0],"h":1},{"i":{"x":0.833,"y":0.833},"o":{"x":0.167,"y":0.167},"t":270,"s":[12.5,-11.5,0],"to":[0,-5.333,0],"ti":[0,5.333,0]},{"t":280,"s":[12.5,-43.5,0],"h":1},{"i":{"x":0.833,"y":0.833},"o":{"x":0.167,"y":0.167},"t":310,"s":[12.5,-43.5,0],"to":[0,-5.333,0],"ti":[0,5.333,0]},{"t":320,"s":[12.5,-75.5,0],"h":1},{"i":{"x":0.833,"y":0.833},"o":{"x":0.167,"y":0.167},"t":350,"s":[12.5,-75.5,0],"to":[0,0,0],"ti":[0,0,0]},{"t":360,"s":[12.5,-107.5,0],"h":1}],"ix":2},"a":{"a":0,"k":[12.5,177.5,0],"ix":1},"s":{"a":0,"k":[100,100,100],"ix":6}},"ao":0,"w":25,"h":355,"ip":0,"op":600,"st":0,"bm":0}]},{"id":"comp_2","layers":[{"ddd":0,"ind":1,"ty":4,"nm":"Num_Count Outlines","sr":1,"ks":{"o":{"a":0,"k":100,"ix":11},"r":{"a":0,"k":0,"ix":10},"p":{"a":0,"k":[12.5,177.5,0],"ix":2},"a":{"a":0,"k":[12.5,177.5,0],"ix":1},"s":{"a":0,"k":[100,100,100],"ix":6}},"ao":0,"shapes":[{"ty":"gr","it":[{"ind":0,"ty":"sh","ix":1,"ks":{"a":0,"k":{"i":[[-1.354,-0.568],[-1.008,-1.131],[-0.551,-1.701],[0,-2.276],[0,0],[0.902,-2.103],[1.67,-1.12],[2.338,0],[1.397,0.618],[0.903,1.069],[0.271,1.386],[0,0],[0,0],[0,0],[-0.403,-0.409],[-0.57,-0.23],[-0.73,0],[-0.829,0.755],[-0.421,1.274],[-0.074,1.571],[0,0.186],[0,0],[0,0],[0.433,0.718],[0.742,0.426],[0.915,0],[0.742,-0.419],[0.445,-0.711],[0,-0.878],[0,0],[-0.426,-0.712],[-0.737,-0.403],[-0.928,0],[-0.742,0.397],[-0.44,0.705],[0,0.903],[0,0],[0,0],[0,0],[0,0],[0.686,-0.643],[0.971,-0.378],[1.212,0],[1.31,0.748],[0.736,1.312],[0,1.67],[0,0],[-0.897,1.404],[-1.553,0.804],[-1.992,0]],"o":[[1.354,0.569],[1.008,1.133],[0.551,1.7],[0,0],[0,2.92],[-0.904,2.103],[-1.67,1.119],[-1.719,0],[-1.399,-0.618],[-0.903,-1.071],[0,0],[0,0],[0,0],[0.223,0.532],[0.402,0.408],[0.568,0.228],[1.311,0],[0.828,-0.754],[0.42,-1.274],[0.012,-0.185],[0,0],[0,0],[0,-0.903],[-0.433,-0.717],[-0.743,-0.427],[-0.916,0],[-0.742,0.421],[-0.446,0.712],[0,0],[0,0.927],[0.427,0.711],[0.736,0.401],[0.939,0],[0.742,-0.395],[0.439,-0.705],[0,0],[0,0],[0,0],[0,0],[-0.346,0.829],[-0.687,0.643],[-0.97,0.377],[-1.72,0],[-1.312,-0.749],[-0.737,-1.31],[0,0],[0,-1.83],[0.896,-1.403],[1.552,-0.804],[1.62,0]],"v":[[4.044,-12.997],[7.588,-10.447],[9.926,-6.197],[10.752,-0.232],[10.752,-0.195],[9.398,7.339],[5.538,12.172],[-0.474,13.852],[-5.149,12.923],[-8.601,10.391],[-10.363,6.707],[-10.4,6.54],[-4.852,6.54],[-4.797,6.689],[-3.86,8.099],[-2.403,9.055],[-0.455,9.398],[2.755,8.266],[4.629,5.223],[5.371,0.956],[5.39,0.398],[5.39,-0.158],[4.555,-4.611],[3.905,-7.042],[2.143,-8.758],[-0.344,-9.398],[-2.83,-8.768],[-4.611,-7.07],[-5.279,-4.685],[-5.279,-4.648],[-4.64,-2.189],[-2.895,-0.519],[-0.399,0.083],[2.124,-0.51],[3.896,-2.161],[4.555,-4.574],[4.555,-4.611],[5.687,-4.611],[5.687,-0.065],[5.278,-0.065],[3.729,2.143],[1.242,3.674],[-2.032,4.24],[-6.578,3.117],[-9.649,0.027],[-10.752,-4.444],[-10.752,-4.48],[-9.408,-9.333],[-5.734,-12.645],[-0.418,-13.852]],"c":true},"ix":2},"nm":"Path 1","mn":"ADBE Vector Shape - Group","hd":false},{"ind":1,"ty":"sh","ix":2,"ks":{"a":0,"k":{"i":[[-0.644,0.31],[-0.358,0.545],[0,0.718],[0,0],[0.364,0.545],[0.644,0.31],[0.83,0],[0.643,-0.308],[0.364,-0.543],[0,-0.717],[0,0],[-0.365,-0.544],[-0.644,-0.309],[-0.84,0]],"o":[[0.644,-0.309],[0.358,-0.544],[0,0],[0,-0.717],[-0.365,-0.543],[-0.643,-0.308],[-0.84,0],[-0.644,0.31],[-0.365,0.545],[0,0],[0,0.718],[0.364,0.545],[0.643,0.31],[0.841,0]],"v":[[2.114,-34.959],[3.617,-36.239],[4.155,-38.132],[4.155,-38.169],[3.608,-40.062],[2.095,-41.342],[-0.113,-41.806],[-2.339,-41.342],[-3.851,-40.062],[-4.399,-38.169],[-4.399,-38.132],[-3.851,-36.239],[-2.339,-34.959],[-0.113,-34.495]],"c":true},"ix":2},"nm":"Path 2","mn":"ADBE Vector Shape - Group","hd":false},{"ind":2,"ty":"sh","ix":3,"ks":{"a":0,"k":{"i":[[-0.743,0.347],[-0.426,0.619],[0,0.779],[0,0],[0.421,0.612],[0.748,0.352],[0.978,0],[0.748,-0.353],[0.421,-0.613],[0,-0.791],[0,0],[-0.427,-0.618],[-0.749,-0.346],[-0.977,0]],"o":[[0.742,-0.346],[0.427,-0.618],[0,0],[0,-0.791],[-0.421,-0.613],[-0.749,-0.353],[-0.989,0],[-0.749,0.352],[-0.421,0.612],[0,0],[0,0.779],[0.427,0.619],[0.748,0.347],[0.978,0]],"v":[[2.467,-22.75],[4.22,-24.197],[4.86,-26.294],[4.86,-26.331],[4.229,-28.437],[2.476,-29.884],[-0.113,-30.413],[-2.719,-29.884],[-4.473,-28.437],[-5.104,-26.331],[-5.104,-26.294],[-4.463,-24.197],[-2.7,-22.75],[-0.113,-22.23]],"c":true},"ix":2},"nm":"Path 3","mn":"ADBE Vector Shape - Group","hd":false},{"ind":3,"ty":"sh","ix":4,"ks":{"a":0,"k":{"i":[[1.62,0.655],[0.915,1.168],[0,1.534],[0,0],[-0.532,0.928],[-0.928,0.619],[-1.2,0.223],[0,0],[0.965,1.046],[0,1.436],[0,0],[-0.835,1.076],[-1.478,0.619],[-1.929,0],[-1.472,-0.618],[-0.835,-1.076],[0,-1.373],[0,0],[0.958,-1.045],[1.545,-0.396],[0,0],[-0.928,-0.618],[-0.527,-0.927],[0,-1.162],[0,0],[0.91,-1.17],[1.62,-0.655],[2.128,0]],"o":[[-1.62,-0.655],[-0.915,-1.17],[0,0],[0,-1.162],[0.533,-0.927],[0.928,-0.618],[0,0],[-1.546,-0.396],[-0.965,-1.045],[0,0],[0,-1.373],[0.835,-1.076],[1.478,-0.618],[1.93,0],[1.472,0.619],[0.835,1.076],[0,0],[0,1.436],[-0.959,1.046],[0,0],[1.2,0.223],[0.928,0.619],[0.525,0.928],[0,0],[0,1.534],[-0.909,1.168],[-1.621,0.655],[-2.127,0]],"v":[[-5.735,-19.132],[-9.538,-21.868],[-10.911,-25.923],[-10.911,-25.96],[-10.114,-29.096],[-7.924,-31.415],[-4.733,-32.677],[-4.733,-32.788],[-8.499,-34.95],[-9.947,-38.67],[-9.947,-38.707],[-8.694,-42.381],[-5.224,-44.923],[-0.113,-45.851],[4.99,-44.923],[8.451,-42.381],[9.703,-38.707],[9.703,-38.67],[8.265,-34.95],[4.508,-32.788],[4.508,-32.677],[7.699,-31.415],[9.88,-29.096],[10.668,-25.96],[10.668,-25.923],[9.304,-21.868],[5.51,-19.132],[-0.113,-18.148]],"c":true},"ix":2},"nm":"Path 4","mn":"ADBE Vector Shape - Group","hd":false},{"ind":4,"ty":"sh","ix":5,"ks":{"a":0,"k":{"i":[[0,0],[0,0],[0,0],[0,0],[0,0],[0,0],[0,0],[0,0]],"o":[[0,0],[0,0],[0,0],[0,0],[0,0],[0,0],[0,0],[0,0]],"v":[[3.812,-72.823],[3.812,-72.934],[-9.826,-72.934],[-9.826,-77.387],[9.342,-77.387],[9.342,-72.879],[-1.829,-50.613],[-7.71,-50.613]],"c":true},"ix":2},"nm":"Path 5","mn":"ADBE Vector Shape - Group","hd":false},{"ind":5,"ty":"sh","ix":6,"ks":{"a":0,"k":{"i":[[1.36,0.568],[1.002,1.133],[0.557,1.7],[0,2.277],[0,0],[-0.909,2.104],[-1.675,1.119],[-2.326,0],[-1.386,-0.611],[-0.91,-1.077],[-0.259,-1.385],[0,0],[0,0],[0,0],[0.402,0.402],[0.568,0.229],[0.729,0],[0.835,-0.754],[0.42,-1.269],[0.074,-1.583],[0.006,-0.186],[0,-0.185],[0,0],[-0.433,-0.722],[-0.742,-0.428],[-0.916,0],[-0.742,0.42],[-0.439,0.712],[0,0.879],[0,0],[0.427,0.711],[0.73,0.402],[0.928,0],[0.754,-0.396],[0.433,-0.705],[0,-0.902],[0,0],[0,0],[0,0],[0,0],[-0.686,0.644],[-0.971,0.377],[-1.2,0],[-1.305,-0.749],[-0.737,-1.311],[0,-1.67],[0,0],[0.891,-1.403],[1.553,-0.803],[1.991,0]],"o":[[-1.361,-0.568],[-1.002,-1.131],[-0.556,-1.701],[0,0],[0,-2.919],[0.91,-2.102],[1.676,-1.12],[1.732,0],[1.385,0.614],[0.909,1.076],[0,0],[0,0],[0,0],[-0.211,-0.543],[-0.402,-0.402],[-0.569,-0.229],[-1.299,0],[-0.835,0.755],[-0.421,1.267],[-0.013,0.185],[-0.006,0.185],[0,0],[0,0.891],[0.433,0.725],[0.742,0.426],[0.915,0],[0.742,-0.42],[0.44,-0.711],[0,0],[0,-0.927],[-0.427,-0.712],[-0.73,-0.402],[-0.928,0],[-0.755,0.396],[-0.433,0.705],[0,0],[0,0],[0,0],[0,0],[0.358,-0.828],[0.687,-0.642],[0.97,-0.378],[1.732,0],[1.305,0.748],[0.736,1.311],[0,0],[0,1.831],[-0.89,1.404],[-1.553,0.804],[-1.621,0]],"v":[[-4.296,-83.002],[-7.84,-85.554],[-10.178,-89.802],[-11.012,-95.768],[-11.012,-95.805],[-9.65,-103.338],[-5.772,-108.171],[0.231,-109.851],[4.907,-108.933],[8.349,-106.399],[10.102,-102.707],[10.14,-102.54],[4.61,-102.54],[4.536,-102.689],[3.617,-104.108],[2.161,-105.054],[0.213,-105.398],[-2.988,-104.266],[-4.871,-101.231],[-5.613,-96.955],[-5.642,-96.398],[-5.65,-95.842],[-4.797,-91.389],[-4.148,-88.968],[-2.385,-87.241],[0.101,-86.602],[2.588,-87.232],[4.359,-88.931],[5.018,-91.315],[5.018,-91.352],[4.378,-93.81],[2.643,-95.48],[0.157,-96.083],[-2.366,-95.489],[-4.148,-93.838],[-4.797,-91.426],[-4.797,-91.389],[-5.929,-91.389],[-5.929,-95.935],[-5.539,-95.935],[-3.972,-98.143],[-1.485,-99.673],[1.771,-100.239],[6.326,-99.116],[9.388,-96.027],[10.492,-91.556],[10.492,-91.519],[9.156,-86.667],[5.491,-83.355],[0.176,-82.148]],"c":true},"ix":2},"nm":"Path 6","mn":"ADBE Vector Shape - Group","hd":false},{"ind":6,"ty":"sh","ix":7,"ks":{"a":0,"k":{"i":[[1.459,0.692],[0.854,1.187],[0.111,1.484],[0,0],[0,0],[0,0],[-0.44,-0.544],[-0.68,-0.317],[-0.853,0],[-0.748,0.414],[-0.421,0.73],[0,0.953],[0,0],[0.427,0.717],[0.742,0.408],[0.964,0],[0.581,-0.191],[0.458,-0.371],[0.222,-0.253],[0.149,-0.284],[0,0],[0,0],[0,0],[0,0],[0,0],[0,0],[0,0],[-1.052,0.519],[-1.361,0],[-1.312,-0.748],[-0.755,-1.31],[0,-1.682],[0,0],[0.873,-1.41],[1.559,-0.791],[2.041,0]],"o":[[-1.46,-0.692],[-0.853,-1.188],[0,0],[0,0],[0,0],[0.136,0.668],[0.439,0.545],[0.68,0.314],[0.977,0],[0.748,-0.415],[0.42,-0.73],[0,0],[0,-0.939],[-0.427,-0.717],[-0.742,-0.408],[-0.681,0],[-0.582,0.192],[-0.259,0.198],[-0.223,0.253],[0,0],[0,0],[0,0],[0,0],[0,0],[0,0],[0,0],[0.557,-0.903],[1.051,-0.52],[1.707,0],[1.31,0.749],[0.754,1.312],[0,0],[0,1.868],[-0.872,1.41],[-1.559,0.791],[-1.943,0]],"v":[[-4.927,-115.188],[-8.397,-118.008],[-9.844,-122.016],[-9.863,-122.294],[-4.686,-122.294],[-4.649,-122.165],[-3.786,-120.346],[-2.107,-119.056],[0.194,-118.584],[2.782,-119.205],[4.536,-120.921],[5.167,-123.445],[5.167,-123.482],[4.526,-125.968],[2.773,-127.657],[0.213,-128.269],[-1.68,-127.982],[-3.239,-127.137],[-3.962,-126.46],[-4.519,-125.653],[-9.399,-125.653],[-8.174,-141.387],[8.915,-141.387],[8.915,-136.934],[-3.721,-136.934],[-4.37,-129.382],[-4.259,-129.382],[-1.847,-131.516],[1.771,-132.295],[6.299,-131.173],[9.397,-128.084],[10.529,-123.593],[10.529,-123.556],[9.22,-118.639],[5.575,-115.336],[0.176,-114.149]],"c":true},"ix":2},"nm":"Path 7","mn":"ADBE Vector Shape - Group","hd":false},{"ind":7,"ty":"sh","ix":8,"ks":{"a":0,"k":{"i":[[0,0],[0,0],[0,0],[0.557,-0.883],[0.562,-0.89],[0.563,-0.89],[0.562,-0.884],[0.556,-0.891],[0,0]],"o":[[0,0],[0,0],[-0.557,0.891],[-0.556,0.885],[-0.563,0.891],[-0.562,0.891],[-0.563,0.884],[0,0],[0,0]],"v":[[2.328,-155.853],[2.328,-169.324],[2.198,-169.324],[0.528,-166.662],[-1.151,-163.999],[-2.84,-161.327],[-4.528,-158.664],[-6.207,-156.001],[-6.207,-155.853]],"c":true},"ix":2},"nm":"Path 8","mn":"ADBE Vector Shape - Group","hd":false},{"ind":8,"ty":"sh","ix":9,"ks":{"a":0,"k":{"i":[[0,0],[0,0],[0,0],[-0.718,1.15],[-0.718,1.144],[-0.717,1.144],[-0.718,1.151],[-0.706,1.138],[0,0],[0,0],[0,0],[0,0],[0,0],[0,0],[0,0]],"o":[[0,0],[0,0],[0.705,-1.137],[0.717,-1.151],[0.717,-1.144],[0.717,-1.144],[0.717,-1.15],[0,0],[0,0],[0,0],[0,0],[0,0],[0,0],[0,0],[0,0]],"v":[[2.217,-151.511],[-11.087,-151.511],[-11.087,-156.206],[-8.953,-159.638],[-6.801,-163.08],[-4.649,-166.513],[-2.496,-169.955],[-0.362,-173.387],[7.56,-173.387],[7.56,-156.001],[11.086,-156.001],[11.086,-151.511],[7.56,-151.511],[7.56,-146.613],[2.217,-146.613]],"c":true},"ix":2},"nm":"Path 9","mn":"ADBE Vector Shape - Group","hd":false},{"ind":9,"ty":"sh","ix":10,"ks":{"a":0,"k":{"i":[[1.516,0.662],[0.878,1.176],[0.135,1.534],[0,0],[0,0],[0,0],[-0.896,-0.637],[-1.447,0],[-0.705,0.314],[-0.389,0.564],[0,0.73],[0,0],[0.902,0.681],[1.62,0],[0,0],[0,0],[0,0],[-0.687,0.31],[-0.383,0.545],[0,0.718],[0,0],[0.328,0.519],[0.625,0.273],[0.878,0],[0.668,-0.277],[0.396,-0.513],[0.086,-0.692],[0,0],[0,0],[0,0],[-0.834,1.15],[-1.423,0.638],[-1.868,0],[-1.416,-0.587],[-0.779,-1.051],[0,-1.41],[0,0],[0.494,-0.847],[0.848,-0.544],[1.039,-0.21],[0,0],[-1.194,-1.101],[0,-1.818],[0,0],[0.865,-1.205],[1.559,-0.668],[2.09,0]],"o":[[-1.516,-0.661],[-0.879,-1.175],[0,0],[0,0],[0,0],[0.111,0.953],[0.897,0.637],[0.965,0],[0.705,-0.317],[0.39,-0.562],[0,0],[0,-1.274],[-0.904,-0.68],[0,0],[0,0],[0,0],[0.94,0],[0.686,-0.309],[0.383,-0.544],[0,0],[0,-0.73],[-0.328,-0.52],[-0.625,-0.271],[-0.866,0],[-0.668,0.28],[-0.396,0.513],[0,0],[0,0],[0,0],[0.136,-1.546],[0.835,-1.151],[1.422,-0.637],[1.929,0],[1.416,0.588],[0.78,1.052],[0,0],[0,1.114],[-0.495,0.847],[-0.847,0.545],[0,0],[1.991,0.185],[1.193,1.101],[0,0],[0,1.595],[-0.866,1.207],[-1.559,0.668],[-2.029,0]],"v":[[-5.549,-179.142],[-9.139,-181.897],[-10.66,-185.96],[-10.678,-186.202],[-5.317,-186.202],[-5.279,-185.997],[-3.768,-183.613],[-0.251,-182.658],[2.254,-183.13],[3.895,-184.449],[4.48,-186.387],[4.48,-186.424],[3.126,-189.356],[-0.659,-190.376],[-3.721,-190.376],[-3.721,-194.384],[-0.734,-194.384],[1.706,-194.848],[3.311,-196.128],[3.887,-198.021],[3.887,-198.058],[3.394,-199.932],[1.966,-201.12],[-0.288,-201.528],[-2.589,-201.111],[-4.185,-199.923],[-4.908,-198.114],[-4.927,-197.928],[-10.085,-197.928],[-10.067,-198.169],[-8.611,-202.214],[-5.224,-204.896],[-0.288,-205.851],[4.73,-204.97],[8.024,-202.511],[9.193,-198.819],[9.193,-198.782],[8.451,-195.841],[6.437,-193.753],[3.608,-192.621],[3.608,-192.51],[8.386,-190.58],[10.177,-186.202],[10.177,-186.164],[8.878,-181.962],[5.241,-179.151],[-0.233,-178.149]],"c":true},"ix":2},"nm":"Path 10","mn":"ADBE Vector Shape - Group","hd":false},{"ind":10,"ty":"sh","ix":11,"ks":{"a":0,"k":{"i":[[0,0],[0,0],[-0.594,0.718],[-0.217,0.564],[0,0.619],[0,0],[0.346,0.563],[0.606,0.323],[0.792,0],[0.692,-0.372],[0.396,-0.63],[0.025,-0.804],[0,0],[0,0],[0,0],[-0.854,1.292],[-1.491,0.731],[-1.88,0],[-1.434,-0.667],[-0.804,-1.17],[0,-1.522],[0,0],[0.389,-0.922],[0.891,-1.026],[1.546,-1.422],[0,0],[0,0],[0,0],[0,0],[0,0],[0,0],[0,0]],"o":[[0,0],[1.15,-1.076],[0.594,-0.717],[0.216,-0.562],[0,0],[0,-0.742],[-0.347,-0.563],[-0.607,-0.321],[-0.915,0],[-0.692,0.371],[-0.395,0.631],[0,0],[0,0],[0,0],[0,-1.681],[0.853,-1.293],[1.491,-0.729],[1.893,0],[1.435,0.668],[0.803,1.168],[0,0],[0,1.088],[-0.39,0.921],[-0.891,1.027],[0,0],[0,0],[0,0],[0,0],[0,0],[0,0],[0,0],[0,0]],"v":[[-9.687,-214.454],[-0.223,-223.305],[2.393,-225.995],[3.609,-227.916],[3.932,-229.687],[3.932,-229.725],[3.413,-231.682],[1.984,-233.009],[-0.113,-233.491],[-2.525,-232.934],[-4.158,-231.432],[-4.788,-229.279],[-4.807,-229.112],[-10.001,-229.112],[-10.001,-229.261],[-8.721,-233.723],[-5.206,-236.757],[-0.15,-237.851],[4.841,-236.85],[8.201,-234.094],[9.406,-230.058],[9.406,-230.021],[8.822,-227.006],[6.902,-224.084],[3.247,-220.41],[-4.51,-213.341],[-2.357,-217.107],[-2.357,-213.341],[-4.492,-215.066],[9.777,-215.066],[9.777,-210.613],[-9.687,-210.613]],"c":true},"ix":2},"nm":"Path 11","mn":"ADBE Vector Shape - Group","hd":false},{"ind":11,"ty":"sh","ix":12,"ks":{"a":0,"k":{"i":[[0,0],[0,0],[0,0],[0,0],[0,0],[0,0],[0,0],[0,0]],"o":[[0,0],[0,0],[0,0],[0,0],[0,0],[0,0],[0,0],[0,0]],"v":[[-0.669,-264.247],[-0.78,-264.247],[-7.608,-259.608],[-7.608,-264.581],[-0.688,-269.387],[4.897,-269.387],[4.897,-242.612],[-0.669,-242.612]],"c":true},"ix":2},"nm":"Path 12","mn":"ADBE Vector Shape - Group","hd":false},{"ind":12,"ty":"sh","ix":13,"ks":{"a":0,"k":{"i":[[-0.779,0.742],[-0.408,1.398],[0,1.955],[0,0],[0.408,1.392],[0.779,0.742],[1.113,0],[0.786,-0.742],[0.409,-1.392],[0,-1.954],[0,0],[-0.408,-1.397],[-0.786,-0.742],[-1.113,0]],"o":[[0.779,-0.742],[0.408,-1.397],[0,0],[0,-1.954],[-0.408,-1.392],[-0.779,-0.742],[-1.113,0],[-0.786,0.742],[-0.408,1.392],[0,0],[0,1.955],[0.409,1.398],[0.786,0.742],[1.113,0]],"v":[[2.727,40.711],[4.508,37.501],[5.121,32.473],[5.121,32.436],[4.508,27.417],[2.727,24.216],[-0.112,23.103],[-2.96,24.216],[-4.751,27.417],[-5.363,32.436],[-5.363,32.473],[-4.751,37.501],[-2.96,40.711],[-0.112,41.824]],"c":true},"ix":2},"nm":"Path 13","mn":"ADBE Vector Shape - Group","hd":false},{"ind":13,"ty":"sh","ix":14,"ks":{"a":0,"k":{"i":[[1.633,1.126],[0.878,2.066],[0,2.845],[0,0],[-0.878,2.067],[-1.632,1.119],[-2.264,0],[-1.627,-1.119],[-0.878,-2.065],[0,-2.845],[0,0],[0.878,-2.066],[1.626,-1.125],[2.264,0]],"o":[[-1.632,-1.125],[-0.878,-2.066],[0,0],[0,-2.845],[0.878,-2.065],[1.633,-1.119],[2.264,0],[1.626,1.119],[0.878,2.067],[0,0],[0,2.845],[-0.878,2.066],[-1.627,1.126],[-2.264,0]],"v":[[-5.957,44.626],[-9.723,39.839],[-11.04,32.473],[-11.04,32.436],[-9.723,25.069],[-5.957,20.292],[-0.112,18.612],[5.724,20.292],[9.481,25.069],[10.798,32.436],[10.798,32.473],[9.481,39.839],[5.724,44.626],[-0.112,46.315]],"c":true},"ix":2},"nm":"Path 14","mn":"ADBE Vector Shape - Group","hd":false},{"ind":14,"ty":"sh","ix":15,"ks":{"a":0,"k":{"i":[[-0.779,0.742],[-0.408,1.398],[0,1.954],[0,0],[0.408,1.391],[0.779,0.742],[1.113,0],[0.786,-0.742],[0.409,-1.392],[0,-1.954],[0,0],[-0.408,-1.397],[-0.786,-0.742],[-1.113,0]],"o":[[0.779,-0.742],[0.408,-1.397],[0,0],[0,-1.954],[-0.408,-1.392],[-0.779,-0.742],[-1.113,0],[-0.786,0.742],[-0.408,1.391],[0,0],[0,1.954],[0.409,1.398],[0.786,0.742],[1.113,0]],"v":[[2.727,-279.752],[4.508,-282.962],[5.121,-287.99],[5.121,-288.027],[4.508,-293.046],[2.727,-296.247],[-0.112,-297.36],[-2.96,-296.247],[-4.751,-293.046],[-5.363,-288.027],[-5.363,-287.99],[-4.751,-282.962],[-2.96,-279.752],[-0.112,-278.639]],"c":true},"ix":2},"nm":"Path 15","mn":"ADBE Vector Shape - Group","hd":false},{"ind":15,"ty":"sh","ix":16,"ks":{"a":0,"k":{"i":[[1.633,1.126],[0.878,2.066],[0,2.845],[0,0],[-0.878,2.066],[-1.632,1.119],[-2.264,0],[-1.627,-1.12],[-0.878,-2.065],[0,-2.845],[0,0],[0.878,-2.066],[1.626,-1.126],[2.264,0]],"o":[[-1.632,-1.126],[-0.878,-2.066],[0,0],[0,-2.845],[0.878,-2.065],[1.633,-1.12],[2.264,0],[1.626,1.119],[0.878,2.066],[0,0],[0,2.845],[-0.878,2.066],[-1.627,1.126],[-2.264,0]],"v":[[-5.957,-275.836],[-9.723,-280.624],[-11.04,-287.99],[-11.04,-288.027],[-9.723,-295.394],[-5.957,-300.171],[-0.112,-301.851],[5.724,-300.171],[9.481,-295.394],[10.798,-288.027],[10.798,-287.99],[9.481,-280.624],[5.724,-275.836],[-0.112,-274.148]],"c":true},"ix":2},"nm":"Path 16","mn":"ADBE Vector Shape - Group","hd":false},{"ty":"fl","c":{"a":0,"k":[1,1,1,1],"ix":4},"o":{"a":0,"k":100,"ix":5},"r":1,"bm":0,"nm":"Fill 1","mn":"ADBE Vector Graphic - Fill","hd":false},{"ty":"tr","p":{"a":0,"k":[12.58,303.39],"ix":2},"a":{"a":0,"k":[0,0],"ix":1},"s":{"a":0,"k":[100,100],"ix":3},"r":{"a":0,"k":0,"ix":6},"o":{"a":0,"k":100,"ix":7},"sk":{"a":0,"k":0,"ix":4},"sa":{"a":0,"k":0,"ix":5},"nm":"Transform"}],"nm":"Group 1","np":17,"cix":2,"bm":0,"ix":1,"mn":"ADBE Vector Group","hd":false},{"ty":"gr","it":[{"ty":"mm","mm":1,"nm":"Merge Paths 1","mn":"ADBE Vector Filter - Merge","hd":false},{"ty":"fl","c":{"a":0,"k":[1,0,0,1],"ix":4},"o":{"a":0,"k":100,"ix":5},"r":1,"bm":0,"nm":"Fill 1","mn":"ADBE Vector Graphic - Fill","hd":false},{"ty":"tr","p":{"a":0,"k":[12.459,271.39],"ix":2},"a":{"a":0,"k":[0,0],"ix":1},"s":{"a":0,"k":[100,100],"ix":3},"r":{"a":0,"k":0,"ix":6},"o":{"a":0,"k":100,"ix":7},"sk":{"a":0,"k":0,"ix":4},"sa":{"a":0,"k":0,"ix":5},"nm":"Transform"}],"nm":"Group 2","np":2,"cix":2,"bm":0,"ix":2,"mn":"ADBE Vector Group","hd":false},{"ty":"gr","it":[{"ty":"fl","c":{"a":0,"k":[1,0,0,1],"ix":4},"o":{"a":0,"k":100,"ix":5},"r":1,"bm":0,"nm":"Fill 1","mn":"ADBE Vector Graphic - Fill","hd":false},{"ty":"tr","p":{"a":0,"k":[12.338,239.391],"ix":2},"a":{"a":0,"k":[0,0],"ix":1},"s":{"a":0,"k":[100,100],"ix":3},"r":{"a":0,"k":0,"ix":6},"o":{"a":0,"k":100,"ix":7},"sk":{"a":0,"k":0,"ix":4},"sa":{"a":0,"k":0,"ix":5},"nm":"Transform"}],"nm":"Group 3","np":1,"cix":2,"bm":0,"ix":3,"mn":"ADBE Vector Group","hd":false},{"ty":"gr","it":[{"ty":"fl","c":{"a":0,"k":[1,0,0,1],"ix":4},"o":{"a":0,"k":100,"ix":5},"r":1,"bm":0,"nm":"Fill 1","mn":"ADBE Vector Graphic - Fill","hd":false},{"ty":"tr","p":{"a":0,"k":[12.32,207.39],"ix":2},"a":{"a":0,"k":[0,0],"ix":1},"s":{"a":0,"k":[100,100],"ix":3},"r":{"a":0,"k":0,"ix":6},"o":{"a":0,"k":100,"ix":7},"sk":{"a":0,"k":0,"ix":4},"sa":{"a":0,"k":0,"ix":5},"nm":"Transform"}],"nm":"Group 4","np":1,"cix":2,"bm":0,"ix":4,"mn":"ADBE Vector Group","hd":false},{"ty":"gr","it":[{"ty":"fl","c":{"a":0,"k":[1,0,0,1],"ix":4},"o":{"a":0,"k":100,"ix":5},"r":1,"bm":0,"nm":"Fill 1","mn":"ADBE Vector Graphic - Fill","hd":false},{"ty":"tr","p":{"a":0,"k":[12.913,175.622],"ix":2},"a":{"a":0,"k":[0,0],"ix":1},"s":{"a":0,"k":[100,100],"ix":3},"r":{"a":0,"k":0,"ix":6},"o":{"a":0,"k":100,"ix":7},"sk":{"a":0,"k":0,"ix":4},"sa":{"a":0,"k":0,"ix":5},"nm":"Transform"}],"nm":"Group 5","np":1,"cix":2,"bm":0,"ix":5,"mn":"ADBE Vector Group","hd":false},{"ty":"gr","it":[{"ty":"mm","mm":1,"nm":"Merge Paths 1","mn":"ADBE Vector Filter - Merge","hd":false},{"ty":"fl","c":{"a":0,"k":[1,0,0,1],"ix":4},"o":{"a":0,"k":100,"ix":5},"r":1,"bm":0,"nm":"Fill 1","mn":"ADBE Vector Graphic - Fill","hd":false},{"ty":"tr","p":{"a":0,"k":[12.58,143.39],"ix":2},"a":{"a":0,"k":[0,0],"ix":1},"s":{"a":0,"k":[100,100],"ix":3},"r":{"a":0,"k":0,"ix":6},"o":{"a":0,"k":100,"ix":7},"sk":{"a":0,"k":0,"ix":4},"sa":{"a":0,"k":0,"ix":5},"nm":"Transform"}],"nm":"Group 6","np":2,"cix":2,"bm":0,"ix":6,"mn":"ADBE Vector Group","hd":false},{"ty":"gr","it":[{"ty":"fl","c":{"a":0,"k":[1,0,0,1],"ix":4},"o":{"a":0,"k":100,"ix":5},"r":1,"bm":0,"nm":"Fill 1","mn":"ADBE Vector Graphic - Fill","hd":false},{"ty":"tr","p":{"a":0,"k":[12.33,111.39],"ix":2},"a":{"a":0,"k":[0,0],"ix":1},"s":{"a":0,"k":[100,100],"ix":3},"r":{"a":0,"k":0,"ix":6},"o":{"a":0,"k":100,"ix":7},"sk":{"a":0,"k":0,"ix":4},"sa":{"a":0,"k":0,"ix":5},"nm":"Transform"}],"nm":"Group 7","np":1,"cix":2,"bm":0,"ix":7,"mn":"ADBE Vector Group","hd":false},{"ty":"gr","it":[{"ty":"fl","c":{"a":0,"k":[1,0,0,1],"ix":4},"o":{"a":0,"k":100,"ix":5},"r":1,"bm":0,"nm":"Fill 1","mn":"ADBE Vector Graphic - Fill","hd":false},{"ty":"tr","p":{"a":0,"k":[12.468,79.159],"ix":2},"a":{"a":0,"k":[0,0],"ix":1},"s":{"a":0,"k":[100,100],"ix":3},"r":{"a":0,"k":0,"ix":6},"o":{"a":0,"k":100,"ix":7},"sk":{"a":0,"k":0,"ix":4},"sa":{"a":0,"k":0,"ix":5},"nm":"Transform"}],"nm":"Group 8","np":1,"cix":2,"bm":0,"ix":8,"mn":"ADBE Vector Group","hd":false},{"ty":"gr","it":[{"ty":"fl","c":{"a":0,"k":[1,0,0,1],"ix":4},"o":{"a":0,"k":100,"ix":5},"r":1,"bm":0,"nm":"Fill 1","mn":"ADBE Vector Graphic - Fill","hd":false},{"ty":"tr","p":{"a":0,"k":[11.225,47.39],"ix":2},"a":{"a":0,"k":[0,0],"ix":1},"s":{"a":0,"k":[100,100],"ix":3},"r":{"a":0,"k":0,"ix":6},"o":{"a":0,"k":100,"ix":7},"sk":{"a":0,"k":0,"ix":4},"sa":{"a":0,"k":0,"ix":5},"nm":"Transform"}],"nm":"Group 9","np":1,"cix":2,"bm":0,"ix":9,"mn":"ADBE Vector Group","hd":false},{"ty":"gr","it":[{"ty":"mm","mm":1,"nm":"Merge Paths 1","mn":"ADBE Vector Filter - Merge","hd":false},{"ty":"fl","c":{"a":0,"k":[1,0,0,1],"ix":4},"o":{"a":0,"k":100,"ix":5},"r":1,"bm":0,"nm":"Fill 1","mn":"ADBE Vector Graphic - Fill","hd":false},{"ty":"tr","p":{"a":0,"k":[12.459,335.854],"ix":2},"a":{"a":0,"k":[0,0],"ix":1},"s":{"a":0,"k":[100,100],"ix":3},"r":{"a":0,"k":0,"ix":6},"o":{"a":0,"k":100,"ix":7},"sk":{"a":0,"k":0,"ix":4},"sa":{"a":0,"k":0,"ix":5},"nm":"Transform"}],"nm":"Group 10","np":2,"cix":2,"bm":0,"ix":10,"mn":"ADBE Vector Group","hd":false},{"ty":"gr","it":[{"ty":"mm","mm":1,"nm":"Merge Paths 1","mn":"ADBE Vector Filter - Merge","hd":false},{"ty":"fl","c":{"a":0,"k":[1,0,0,1],"ix":4},"o":{"a":0,"k":100,"ix":5},"r":1,"bm":0,"nm":"Fill 1","mn":"ADBE Vector Graphic - Fill","hd":false},{"ty":"tr","p":{"a":0,"k":[12.459,15.391],"ix":2},"a":{"a":0,"k":[0,0],"ix":1},"s":{"a":0,"k":[100,100],"ix":3},"r":{"a":0,"k":0,"ix":6},"o":{"a":0,"k":100,"ix":7},"sk":{"a":0,"k":0,"ix":4},"sa":{"a":0,"k":0,"ix":5},"nm":"Transform"}],"nm":"Group 11","np":2,"cix":2,"bm":0,"ix":11,"mn":"ADBE Vector Group","hd":false}],"ip":0,"op":600,"st":0,"bm":0}]},{"id":"comp_3","layers":[{"ddd":0,"ind":1,"ty":0,"nm":"Num03","refId":"comp_2","sr":1,"ks":{"o":{"a":0,"k":100,"ix":11},"r":{"a":0,"k":0,"ix":10},"p":{"a":1,"k":[{"i":{"x":0.833,"y":0.833},"o":{"x":0.167,"y":0.167},"t":0,"s":[12.5,180.5,0],"to":[0,-48,0],"ti":[0,48,0]},{"t":40,"s":[12.5,-107.5,0]}],"ix":2},"a":{"a":0,"k":[12.5,177.5,0],"ix":1},"s":{"a":0,"k":[100,100,100],"ix":6}},"ao":0,"w":25,"h":355,"ip":0,"op":296,"st":0,"bm":0}]}],"layers":[{"ddd":0,"ind":1,"ty":4,"nm":"check Outlines","sr":1,"ks":{"o":{"a":0,"k":100,"ix":11},"r":{"a":0,"k":0,"ix":10},"p":{"a":0,"k":[60,60,0],"ix":2},"a":{"a":0,"k":[60,60,0],"ix":1},"s":{"a":0,"k":[100,100,100],"ix":6}},"ao":0,"shapes":[{"ty":"gr","it":[{"ind":0,"ty":"sh","ix":1,"ks":{"a":0,"k":{"i":[[0,0],[0,0],[0,0]],"o":[[0,0],[0,0],[0,0]],"v":[[-25,0],[-8.333,16.5],[25,-16.5]],"c":false},"ix":2},"nm":"Path 1","mn":"ADBE Vector Shape - Group","hd":false},{"ty":"st","c":{"a":0,"k":[1,1,1,1],"ix":3},"o":{"a":0,"k":100,"ix":4},"w":{"a":0,"k":6,"ix":5},"lc":2,"lj":2,"bm":0,"nm":"Stroke 1","mn":"ADBE Vector Graphic - Stroke","hd":false},{"ty":"tr","p":{"a":0,"k":[61,60.5],"ix":2},"a":{"a":0,"k":[0,0],"ix":1},"s":{"a":0,"k":[100,100],"ix":3},"r":{"a":0,"k":0,"ix":6},"o":{"a":0,"k":100,"ix":7},"sk":{"a":0,"k":0,"ix":4},"sa":{"a":0,"k":0,"ix":5},"nm":"Transform"}],"nm":"Group 1","np":2,"cix":2,"bm":0,"ix":1,"mn":"ADBE Vector Group","hd":false},{"ty":"tm","s":{"a":0,"k":0,"ix":1},"e":{"a":1,"k":[{"i":{"x":[0.667],"y":[1]},"o":{"x":[0.333],"y":[0]},"t":410,"s":[0]},{"t":419,"s":[100]}],"ix":2},"o":{"a":0,"k":0,"ix":3},"m":1,"ix":2,"nm":"Trim Paths 1","mn":"ADBE Vector Filter - Trim","hd":false}],"ip":402,"op":464,"st":402,"bm":0},{"ddd":0,"ind":2,"ty":0,"nm":"Count_all","refId":"comp_0","sr":1,"ks":{"o":{"a":1,"k":[{"i":{"x":[0.833],"y":[0.833]},"o":{"x":[0.167],"y":[0.167]},"t":419,"s":[100]},{"t":428,"s":[0]}],"ix":11},"r":{"a":0,"k":0,"ix":10},"p":{"a":0,"k":[60,60,0],"ix":2},"a":{"a":0,"k":[25,18,0],"ix":1},"s":{"a":0,"k":[100,100,100],"ix":6}},"ao":0,"hasMask":true,"masksProperties":[{"inv":false,"mode":"a","pt":{"a":0,"k":{"i":[[0,0],[0,0],[0,0],[0,0]],"o":[[0,0],[0,0],[0,0],[0,0]],"v":[[50.375,2],[-0.292,2],[-0.333,35.062],[50.333,35.062]],"c":true},"ix":1},"o":{"a":0,"k":100,"ix":3},"x":{"a":0,"k":0,"ix":4},"nm":"Mask 1"}],"tm":{"a":1,"k":[{"i":{"x":[0.833],"y":[0.833]},"o":{"x":[0.167],"y":[0.167]},"t":0,"s":[0]},{"t":600,"s":[10]}],"ix":2},"w":50,"h":36,"ip":0,"op":402,"st":0,"bm":0},{"ddd":0,"ind":3,"ty":4,"nm":"progress","sr":1,"ks":{"o":{"a":0,"k":100,"ix":11},"r":{"a":0,"k":0,"ix":10},"p":{"a":0,"k":[60,60,0],"ix":2},"a":{"a":0,"k":[0,0,0],"ix":1},"s":{"a":0,"k":[100,100,100],"ix":6}},"ao":0,"shapes":[{"ty":"gr","it":[{"d":1,"ty":"el","s":{"a":0,"k":[112,112],"ix":2},"p":{"a":0,"k":[0,0],"ix":3},"nm":"Ellipse Path 1","mn":"ADBE Vector Shape - Ellipse","hd":false},{"ty":"st","c":{"a":0,"k":[1,1,1,1],"ix":3},"o":{"a":0,"k":100,"ix":4},"w":{"a":1,"k":[{"i":{"x":[0.833],"y":[0.833]},"o":{"x":[0.167],"y":[0.167]},"t":401,"s":[6]},{"t":410,"s":[0]}],"ix":5},"lc":2,"lj":1,"ml":4,"bm":0,"nm":"Stroke 1","mn":"ADBE Vector Graphic - Stroke","hd":false},{"ty":"tr","p":{"a":0,"k":[0,0],"ix":2},"a":{"a":0,"k":[0,0],"ix":1},"s":{"a":0,"k":[100,100],"ix":3},"r":{"a":0,"k":0,"ix":6},"o":{"a":0,"k":100,"ix":7},"sk":{"a":0,"k":0,"ix":4},"sa":{"a":0,"k":0,"ix":5},"nm":"Transform"}],"nm":"Ellipse 1","np":3,"cix":2,"bm":0,"ix":1,"mn":"ADBE Vector Group","hd":false},{"ty":"tm","s":{"a":0,"k":0,"ix":1},"e":{"a":1,"k":[{"i":{"x":[0.833],"y":[0.833]},"o":{"x":[0.167],"y":[0.167]},"t":0,"s":[0]},{"t":401,"s":[100]}],"ix":2},"o":{"a":0,"k":0,"ix":3},"m":1,"ix":2,"nm":"Trim Paths 1","mn":"ADBE Vector Filter - Trim","hd":false}],"ip":0,"op":594,"st":0,"bm":0},{"ddd":0,"ind":4,"ty":4,"nm":"bg","sr":1,"ks":{"o":{"a":1,"k":[{"i":{"x":[0.833],"y":[0.833]},"o":{"x":[0.167],"y":[0.167]},"t":0,"s":[10]},{"i":{"x":[0.833],"y":[0.833]},"o":{"x":[0.167],"y":[0.167]},"t":405,"s":[10]},{"t":419,"s":[0]}],"ix":11},"r":{"a":0,"k":0,"ix":10},"p":{"a":0,"k":[60,60,0],"ix":2},"a":{"a":0,"k":[0,0,0],"ix":1},"s":{"a":0,"k":[100,100,100],"ix":6}},"ao":0,"shapes":[{"ty":"gr","it":[{"d":1,"ty":"el","s":{"a":0,"k":[112,112],"ix":2},"p":{"a":0,"k":[0,0],"ix":3},"nm":"Ellipse Path 1","mn":"ADBE Vector Shape - Ellipse","hd":false},{"ty":"st","c":{"a":0,"k":[1,1,1,1],"ix":3},"o":{"a":0,"k":100,"ix":4},"w":{"a":0,"k":6,"ix":5},"lc":1,"lj":1,"ml":4,"bm":0,"nm":"Stroke 1","mn":"ADBE Vector Graphic - Stroke","hd":false},{"ty":"tr","p":{"a":0,"k":[0,0],"ix":2},"a":{"a":0,"k":[0,0],"ix":1},"s":{"a":0,"k":[100,100],"ix":3},"r":{"a":0,"k":0,"ix":6},"o":{"a":0,"k":100,"ix":7},"sk":{"a":0,"k":0,"ix":4},"sa":{"a":0,"k":0,"ix":5},"nm":"Transform"}],"nm":"Ellipse 1","np":3,"cix":2,"bm":0,"ix":1,"mn":"ADBE Vector Group","hd":false}],"ip":0,"op":401,"st":0,"bm":0}],"markers":[{"tm":389,"cm":"1","dr":0}]}